MANIFEST.in
README.md
setup.cfg
setup.py
forgetful/__init__.py
forgetful.egg-info/PKG-INFO
forgetful.egg-info/SOURCES.txt
forgetful.egg-info/dependency_links.txt
forgetful.egg-info/top_level.txt