Metadata-Version: 1.1
Name: forgetful
Version: 0.1.1
Summary: Background queue system with no resiliancy
Home-page: https://github.com/colinhowe/forgetful
Author: Colin Howe
Author-email: colin@colinhowe.co.uk
License: Apache 2.0
Platform: UNKNOWN
Classifier: Development Status :: 4 - Beta
Classifier: License :: OSI Approved :: Apache Software License
Classifier: Operating System :: OS Independent
Classifier: Topic :: Utilities
